{
  "data": {
    "labels": [
      {
        "id": "Q11426",
        "label": "metal"
      },
      {
        "id": "Q214609",
        "label": "base material"
      },
      {
        "id": "Q208469",
        "label": "SI derived unit"
      },
      {
        "id": "Q47574",
        "label": "unit of measurement"
      },
      {
        "id": "Q13226383",
        "label": "facility"
      },
      {
        "id": "Q618123",
        "label": "geographical object"
      },
      {
        "id": "Q28877",
        "label": "goods"
      },
      {
        "id": "Q2897903",
        "label": "goods and services"
      },
      {
        "id": "Q3245975",
        "label": "finished good"
      },
      {
        "id": "Q2424752",
        "label": "product"
      },
      {
        "id": "Q17489659",
        "label": "group of works"
      },
      {
        "id": "Q16686448",
        "label": "artificial entity"
      },
      {
        "id": "Q2221906",
        "label": "geographic location"
      },
      {
        "id": "Q17334923",
        "label": "location"
      },
      {
        "id": "Q334166",
        "label": "mode of transport"
      },
      {
        "id": "Q21146257",
        "label": "type"
      },
      {
        "id": "Q1496967",
        "label": "territorial entity"
      },
      {
        "id": "Q82794",
        "label": "geographic region"
      },
      {
        "id": "Q19478619",
        "label": "metaclass"
      },
      {
        "id": "Q15401930",
        "label": "product"
      },
      {
        "id": "Q9788",
        "label": "letter"
      },
      {
        "id": "Q28786318",
        "label": "alphanumeric character"
      },
      {
        "id": "Q294440",
        "label": "public space"
      },
      {
        "id": "Q12876",
        "label": "tank"
      },
      {
        "id": "Q130368",
        "label": "armored fighting vehicle"
      },
      {
        "id": "Q27166344",
        "label": "substance"
      },
      {
        "id": "Q35758",
        "label": "matter"
      },
      {
        "id": "Q336",
        "label": "science"
      },
      {
        "id": "Q9081",
        "label": "knowledge"
      },
      {
        "id": "Q6501447",
        "label": "local government"
      },
      {
        "id": "Q43229",
        "label": "organization"
      },
      {
        "id": "Q23009675",
        "label": "gifting"
      },
      {
        "id": "Q52948",
        "label": "interaction"
      },
      {
        "id": "Q7188",
        "label": "government"
      },
      {
        "id": "Q895526",
        "label": "organ"
      },
      {
        "id": "Q15079663",
        "label": "rapid transit line"
      },
      {
        "id": "Q728937",
        "label": "railroad line"
      },
      {
        "id": "Q20937557",
        "label": "series"
      },
      {
        "id": "Q16887380",
        "label": "group"
      },
      {
        "id": "Q1093580",
        "label": "Han surname"
      },
      {
        "id": "Q33283501",
        "label": "family name from a specific origin"
      },
      {
        "id": "Q79007",
        "label": "street"
      },
      {
        "id": "Q34442",
        "label": "road"
      },
      {
        "id": "Q20817253",
        "label": "linguistic unit"
      },
      {
        "id": "Q4173967",
        "label": "language unit"
      },
      {
        "id": "Q1183543",
        "label": "device"
      },
      {
        "id": "Q838948",
        "label": "work of art"
      },
      {
        "id": "Q18593264",
        "label": "item of collection or exhibition"
      },
      {
        "id": "Q4372150",
        "label": "bounty"
      },
      {
        "id": "Q230788",
        "label": "grant"
      },
      {
        "id": "Q13220204",
        "label": "second-level administrative country subdivision"
      },
      {
        "id": "Q1799794",
        "label": "administrative territorial entity of a specific level"
      },
      {
        "id": "Q22698",
        "label": "park"
      },
      {
        "id": "Q22652",
        "label": "green space"
      },
      {
        "id": "Q486972",
        "label": "human settlement"
      },
      {
        "id": "Q2311958",
        "label": "canton"
      },
      {
        "id": "Q56061",
        "label": "administrative territorial entity"
      },
      {
        "id": "Q105420",
        "label": "anthology"
      },
      {
        "id": "Q376799",
        "label": "transport infrastructure"
      },
      {
        "id": "Q121359",
        "label": "infrastructure"
      },
      {
        "id": "Q3695082",
        "label": "sign"
      },
      {
        "id": "Q11424",
        "label": "film"
      },
      {
        "id": "Q2431196",
        "label": "audiovisual work"
      },
      {
        "id": "Q1144560",
        "label": "rate"
      },
      {
        "id": "Q1207505",
        "label": "quality"
      },
      {
        "id": "Q40634",
        "label": "philology"
      },
      {
        "id": "Q944537",
        "label": "Geisteswissenschaft"
      },
      {
        "id": "Q48522",
        "label": "word-sense disambiguation"
      },
      {
        "id": "Q621184",
        "label": "problem"
      },
      {
        "id": "Q906278",
        "label": "country code"
      },
      {
        "id": "Q36205316",
        "label": "administrative territorial entity identifier"
      },
      {
        "id": "Q583865",
        "label": "territorial collectivity of France"
      },
      {
        "id": "Q192498",
        "label": "administrative territorial entity of France"
      },
      {
        "id": "Q15284",
        "label": "municipality"
      },
      {
        "id": "Q2097994",
        "label": "municipal corporation"
      },
      {
        "id": "Q3266850",
        "label": "commune"
      },
      {
        "id": "Q190087",
        "label": "data type"
      },
      {
        "id": "Q175263",
        "label": "data structure"
      },
      {
        "id": "Q177634",
        "label": "community"
      },
      {
        "id": "Q874405",
        "label": "social group"
      },
      {
        "id": "Q188619",
        "label": "hierarchy"
      },
      {
        "id": "Q6671777",
        "label": "structure"
      },
      {
        "id": "Q3565868",
        "label": "rail transport"
      },
      {
        "id": "Q4354683",
        "label": "land transport"
      },
      {
        "id": "Q783794",
        "label": "company"
      },
      {
        "id": "Q155076",
        "label": "juridical person"
      },
      {
        "id": "Q8205328",
        "label": "artificial physical object"
      },
      {
        "id": "Q111352",
        "label": "lexeme"
      },
      {
        "id": "Q5371079",
        "label": "emic unit"
      },
      {
        "id": "Q3241972",
        "label": "character"
      },
      {
        "id": "Q80071",
        "label": "symbol"
      },
      {
        "id": "Q494823",
        "label": "data format"
      },
      {
        "id": "Q23058",
        "label": "canton of Switzerland"
      },
      {
        "id": "Q10864048",
        "label": "first-level administrative country subdivision"
      },
      {
        "id": "Q1774041"
      },
      {
        "id": "Q2303637",
        "label": "syntagma"
      },
      {
        "id": "Q187931",
        "label": "phrase"
      },
      {
        "id": "Q1067164",
        "label": "line"
      },
      {
        "id": "Q1322323",
        "label": "itinerary"
      },
      {
        "id": "Q16798631",
        "label": "equipment"
      },
      {
        "id": "Q174834",
        "label": "authority"
      },
      {
        "id": "Q25107",
        "label": "power"
      },
      {
        "id": "Q3249551",
        "label": "process"
      },
      {
        "id": "Q1150070",
        "label": "change"
      },
      {
        "id": "Q205895",
        "label": "landmass"
      },
      {
        "id": "Q20719696",
        "label": "physico-geographical object"
      },
      {
        "id": "Q11578774",
        "label": "broadcasting program"
      },
      {
        "id": "Q732577",
        "label": "publication"
      },
      {
        "id": "Q35120",
        "label": "entity"
      },
      {
        "id": "Q23958852",
        "label": "variable-order metaclass"
      },
      {
        "id": "Q2101564",
        "label": "specification"
      },
      {
        "id": "Q49848",
        "label": "document"
      },
      {
        "id": "Q56668826",
        "label": "chess title"
      },
      {
        "id": "Q4121104",
        "label": "sports title"
      },
      {
        "id": "Q167270",
        "label": "trademark"
      },
      {
        "id": "Q200726",
        "label": "probability distribution"
      },
      {
        "id": "Q3284399",
        "label": "statistical model"
      },
      {
        "id": "Q317623",
        "label": "technical standard"
      },
      {
        "id": "Q41796",
        "label": "sentence"
      },
      {
        "id": "Q15916540",
        "label": "semantic unit"
      },
      {
        "id": "Q244982",
        "label": "period 5"
      },
      {
        "id": "Q101843",
        "label": "period"
      },
      {
        "id": "Q28314507",
        "label": "recurring"
      },
      {
        "id": "Q26907166",
        "label": "temporal entity"
      },
      {
        "id": "Q107390",
        "label": "federated state"
      },
      {
        "id": "Q5",
        "label": "human"
      },
      {
        "id": "Q215627",
        "label": "person"
      },
      {
        "id": "Q1263068",
        "label": "duplicate"
      },
      {
        "id": "Q27949697",
        "label": "Wikidata reason for deprecation"
      },
      {
        "id": "Q23958946",
        "label": "individual"
      },
      {
        "id": "Q6881511",
        "label": "enterprise"
      },
      {
        "id": "Q222910",
        "label": "compilation album"
      },
      {
        "id": "Q482994",
        "label": "album"
      },
      {
        "id": "Q39875001",
        "label": "measure"
      },
      {
        "id": "Q488383",
        "label": "object"
      },
      {
        "id": "Q15989253",
        "label": "part"
      },
      {
        "id": "Q8027727",
        "label": "Wissenschaft"
      },
      {
        "id": "Q192161",
        "label": "formal language"
      },
      {
        "id": "Q649732",
        "label": "formal system"
      },
      {
        "id": "Q2217301",
        "label": "serial"
      },
      {
        "id": "Q350783",
        "label": "rail guided transport"
      },
      {
        "id": "Q1146011",
        "label": "exclusive right"
      },
      {
        "id": "Q780687",
        "label": "rights"
      },
      {
        "id": "Q1454188",
        "label": "free area"
      },
      {
        "id": "Q937228",
        "label": "property"
      },
      {
        "id": "Q5398426",
        "label": "television series"
      },
      {
        "id": "Q431289",
        "label": "brand"
      },
      {
        "id": "Q340169",
        "label": "communication medium"
      },
      {
        "id": "Q11028",
        "label": "information"
      },
      {
        "id": "Q6422240",
        "label": "property"
      },
      {
        "id": "Q1235196",
        "label": "documentation science"
      },
      {
        "id": "Q7725634",
        "label": "literary work"
      },
      {
        "id": "Q47461344",
        "label": "written work"
      },
      {
        "id": "Q107715",
        "label": "physical quantity"
      },
      {
        "id": "Q4373292",
        "label": "physical property"
      },
      {
        "id": "Q1499548",
        "label": "monetary value"
      },
      {
        "id": "Q194112",
        "label": "value"
      },
      {
        "id": "Q391371",
        "label": "Bernoulli distribution"
      },
      {
        "id": "Q185547",
        "label": "binomial distribution"
      },
      {
        "id": "Q211364",
        "label": "principle"
      },
      {
        "id": "Q17376908",
        "label": "languoid"
      },
      {
        "id": "Q7184903",
        "label": "abstract object"
      },
      {
        "id": "Q159954",
        "label": "caldera"
      },
      {
        "id": "Q29025902",
        "label": "volcanic landform"
      },
      {
        "id": "Q5469988",
        "label": "formalization"
      },
      {
        "id": "Q4393498",
        "label": "representation"
      },
      {
        "id": "Q11946645",
        "label": "university institute"
      },
      {
        "id": "Q1664720",
        "label": "institute"
      },
      {
        "id": "Q3247505",
        "label": "artificial language"
      },
      {
        "id": "Q17537576",
        "label": "creative work"
      },
      {
        "id": "Q80083",
        "label": "humanities"
      },
      {
        "id": "Q2225692",
        "label": "fourth-level administrative division in Indonesia"
      },
      {
        "id": "Q1434505",
        "label": "administrative territorial entity of Indonesia"
      },
      {
        "id": "Q386724",
        "label": "work"
      },
      {
        "id": "Q795052",
        "label": "individual"
      },
      {
        "id": "Q7887142",
        "label": "unit of analysis"
      },
      {
        "id": "Q36161",
        "label": "set"
      },
      {
        "id": "Q17008256",
        "label": "collection"
      },
      {
        "id": "Q618299",
        "label": "settlement"
      },
      {
        "id": "Q15642541",
        "label": "human-geographic territorial entity"
      },
      {
        "id": "Q28728771",
        "label": "material substance"
      },
      {
        "id": "Q15633587",
        "label": "MediaWiki main-namespace page"
      },
      {
        "id": "Q15474042",
        "label": "MediaWiki page"
      },
      {
        "id": "Q1589009",
        "label": "privately held company"
      },
      {
        "id": "Q56876011",
        "label": "private corporation"
      },
      {
        "id": "Q37930",
        "label": "postage stamp"
      },
      {
        "id": "Q15964794",
        "label": "paper product"
      },
      {
        "id": "Q714737",
        "label": "category of being"
      },
      {
        "id": "Q151885",
        "label": "concept"
      },
      {
        "id": "Q36214810",
        "label": "geographic identifier"
      },
      {
        "id": "Q1444571",
        "label": "franking"
      },
      {
        "id": "Q49845",
        "label": "mail"
      },
      {
        "id": "Q202444",
        "label": "given name"
      },
      {
        "id": "Q10856962",
        "label": "anthroponym"
      },
      {
        "id": "Q1783551",
        "label": "data conversion"
      },
      {
        "id": "Q11436",
        "label": "aircraft"
      },
      {
        "id": "Q42889",
        "label": "vehicle"
      },
      {
        "id": "Q16889133",
        "label": "class"
      },
      {
        "id": "Q699405",
        "label": "residence"
      },
      {
        "id": "Q29175",
        "label": "derivative"
      },
      {
        "id": "Q203066",
        "label": "relation"
      },
      {
        "id": "Q352618",
        "label": "indicia"
      },
      {
        "id": "Q28732711",
        "label": "physical substance"
      },
      {
        "id": "Q4406616",
        "label": "concrete object"
      },
      {
        "id": "Q2063340",
        "label": "sensemaking"
      },
      {
        "id": "Q24034552",
        "label": "mathematical concept"
      },
      {
        "id": "Q494756",
        "label": "data"
      },
      {
        "id": "Q22272508",
        "label": "multi-organism behavior"
      },
      {
        "id": "Q2990593",
        "label": "animal behavior"
      },
      {
        "id": "Q18643213",
        "label": "military equipment"
      },
      {
        "id": "Q154954",
        "label": "natural person"
      },
      {
        "id": "Q3778211",
        "label": "legal person"
      },
      {
        "id": "Q108163",
        "label": "proposition"
      },
      {
        "id": "Q5915039",
        "label": "inconstancy"
      },
      {
        "id": "Q7275",
        "label": "state"
      },
      {
        "id": "Q58416391",
        "label": "spatial entity"
      },
      {
        "id": "Q58415929",
        "label": "spacio-temporal entity"
      },
      {
        "id": "Q7406919",
        "label": "service"
      },
      {
        "id": "Q48907157",
        "label": "section of populated place"
      },
      {
        "id": "Q194980",
        "label": "intangible good"
      },
      {
        "id": "Q23009552",
        "label": "exchange"
      },
      {
        "id": "Q16877783",
        "label": "meaning"
      },
      {
        "id": "Q1414816",
        "label": "incentive"
      },
      {
        "id": "Q2198779",
        "label": "unit"
      },
      {
        "id": "Q5358404",
        "label": "electronic page"
      },
      {
        "id": "Q1209283",
        "label": "electronic media"
      },
      {
        "id": "Q6031064",
        "label": "information exchange"
      },
      {
        "id": "Q1002697",
        "label": "periodical literature"
      },
      {
        "id": "Q9143",
        "label": "programming language"
      },
      {
        "id": "Q629206",
        "label": "computer language"
      },
      {
        "id": "Q2545446",
        "label": "grapheme"
      },
      {
        "id": "Q33104279",
        "label": "philosophical concept"
      },
      {
        "id": "Q19549",
        "label": "chemical series"
      },
      {
        "id": "Q1190554",
        "label": "occurrence"
      },
      {
        "id": "Q739302",
        "label": "production"
      },
      {
        "id": "Q14296",
        "label": "top-level domain"
      },
      {
        "id": "Q32635",
        "label": "domain name"
      },
      {
        "id": "Q1084",
        "label": "noun"
      },
      {
        "id": "Q1401131",
        "label": "noun phrase"
      },
      {
        "id": "Q2995644",
        "label": "result"
      },
      {
        "id": "Q374182",
        "label": "logical consequence"
      },
      {
        "id": "Q484170",
        "label": "commune of France"
      },
      {
        "id": "Q14757767",
        "label": "fourth-level administrative country subdivision"
      },
      {
        "id": "Q451967",
        "label": "human action"
      },
      {
        "id": "Q4026292",
        "label": "action"
      },
      {
        "id": "Q38033430",
        "label": "class of award"
      },
      {
        "id": "Q838795",
        "label": "comic strip"
      },
      {
        "id": "Q1004",
        "label": "comic"
      },
      {
        "id": "Q846537",
        "label": "generalized function"
      },
      {
        "id": "Q217594",
        "label": "class (set theory)"
      },
      {
        "id": "Q29651519",
        "label": "mental object"
      },
      {
        "id": "Q29651224",
        "label": "natural object"
      },
      {
        "id": "Q1322005",
        "label": "natural phenomenon"
      },
      {
        "id": "Q79529",
        "label": "chemical substance"
      },
      {
        "id": "Q2385804",
        "label": "educational institution"
      },
      {
        "id": "Q781413",
        "label": "mental process"
      },
      {
        "id": "Q39546",
        "label": "tool"
      },
      {
        "id": "Q2684591",
        "label": "statement"
      },
      {
        "id": "Q7725310",
        "label": "series of creative works"
      },
      {
        "id": "Q5127848",
        "label": "class"
      },
      {
        "id": "Q131257",
        "label": "intellectual property"
      },
      {
        "id": "Q11344",
        "label": "chemical element"
      },
      {
        "id": "Q2031291",
        "label": "release"
      },
      {
        "id": "Q216353",
        "label": "title"
      },
      {
        "id": "Q15141321",
        "label": "train service"
      },
      {
        "id": "Q165436",
        "label": "assembly language"
      },
      {
        "id": "Q28922854",
        "label": "non-structured programming language"
      },
      {
        "id": "Q7551384",
        "label": "social space"
      },
      {
        "id": "Q4502142",
        "label": "visual artwork"
      },
      {
        "id": "Q332624",
        "label": "Erga omnes"
      },
      {
        "id": "Q7748",
        "label": "law"
      },
      {
        "id": "Q15042037",
        "label": "statistical territorial entity"
      },
      {
        "id": "Q15709883",
        "label": "statistical definition"
      },
      {
        "id": "Q1979154",
        "label": "model"
      },
      {
        "id": "Q31464082",
        "label": "source"
      },
      {
        "id": "Q17320256",
        "label": "physical process"
      },
      {
        "id": "Q104567",
        "label": "group 16"
      },
      {
        "id": "Q83306",
        "label": "group"
      },
      {
        "id": "Q58778",
        "label": "system"
      },
      {
        "id": "Q15916867",
        "label": "administrative territorial entity of a single country"
      },
      {
        "id": "Q51049922",
        "label": "village"
      },
      {
        "id": "Q11348",
        "label": "function"
      },
      {
        "id": "Q130901",
        "label": "binary relation"
      },
      {
        "id": "Q2342494",
        "label": "collectable"
      },
      {
        "id": "Q43460564",
        "label": "chemical entity"
      },
      {
        "id": "Q223557",
        "label": "physical object"
      },
      {
        "id": "Q1454986",
        "label": "physical system"
      },
      {
        "id": "Q19588",
        "label": "transition metal"
      },
      {
        "id": "Q188913",
        "label": "plantation"
      },
      {
        "id": "Q131596",
        "label": "farm"
      },
      {
        "id": "Q14788575",
        "label": "rural settlement"
      },
      {
        "id": "Q178706",
        "label": "institution"
      },
      {
        "id": "Q34669510"
      },
      {
        "id": "Q2659904",
        "label": "government organization"
      },
      {
        "id": "Q207628",
        "label": "musical composition"
      },
      {
        "id": "Q2188189",
        "label": "musical work"
      },
      {
        "id": "Q79913",
        "label": "non-governmental organization"
      },
      {
        "id": "Q163740",
        "label": "nonprofit organization"
      },
      {
        "id": "Q19793988",
        "label": "Cyrillic letter"
      },
      {
        "id": "Q83620",
        "label": "thoroughfare"
      },
      {
        "id": "Q286583",
        "label": "manifestation"
      },
      {
        "id": "Q1048835",
        "label": "political territorial entity"
      },
      {
        "id": "Q33274034",
        "label": "anthroponym from a specific origin"
      },
      {
        "id": "Q236371",
        "label": "orchard"
      },
      {
        "id": "Q101072",
        "label": "definition"
      },
      {
        "id": "Q1786828",
        "label": "constituent"
      },
      {
        "id": "Q7194062",
        "label": "flying machine"
      },
      {
        "id": "Q11019",
        "label": "machine"
      },
      {
        "id": "Q246672",
        "label": "mathematical object"
      },
      {
        "id": "Q23847174",
        "label": "religious concept"
      },
      {
        "id": "Q1311670",
        "label": "rail infrastructure"
      },
      {
        "id": "Q853614",
        "label": "identifier"
      },
      {
        "id": "Q16334298",
        "label": "living thing group"
      },
      {
        "id": "Q517966"
      },
      {
        "id": "Q23009459",
        "label": "connect"
      },
      {
        "id": "Q722",
        "label": "vanadium"
      },
      {
        "id": "Q193276",
        "label": "group 5"
      },
      {
        "id": "Q191067",
        "label": "article"
      },
      {
        "id": "Q7550889",
        "label": "combat vehicle"
      },
      {
        "id": "Q7978115",
        "label": "weapons platform"
      },
      {
        "id": "Q188889",
        "label": "code"
      },
      {
        "id": "Q34770",
        "label": "language"
      },
      {
        "id": "Q1293220",
        "label": "physical phenomenon"
      },
      {
        "id": "Q16722960",
        "label": "phenomenon"
      },
      {
        "id": "Q7366",
        "label": "song"
      },
      {
        "id": "Q181175",
        "label": "scalar physical quantity"
      },
      {
        "id": "Q1289248",
        "label": "scalar"
      },
      {
        "id": "Q733541"
      },
      {
        "id": "Q760120",
        "label": "expenditure"
      },
      {
        "id": "Q240673",
        "label": "cost"
      },
      {
        "id": "Q154015",
        "label": "international vehicle registration code"
      },
      {
        "id": "Q2695280",
        "label": "technique"
      },
      {
        "id": "Q1914636",
        "label": "activity"
      },
      {
        "id": "Q234460",
        "label": "text"
      },
      {
        "id": "Q15709880",
        "label": "serial"
      },
      {
        "id": "Q19361238",
        "label": "Wikidata metaclass"
      },
      {
        "id": "Q82042",
        "label": "part of speech"
      },
      {
        "id": "Q427581",
        "label": "intangible asset"
      },
      {
        "id": "Q4120621",
        "label": "rank"
      },
      {
        "id": "Q24017414",
        "label": "first-order metaclass"
      },
      {
        "id": "Q17538690",
        "label": "group of manifestations"
      },
      {
        "id": "Q7210356",
        "label": "political organisation"
      },
      {
        "id": "Q26898117",
        "label": "discrete probability distribution"
      },
      {
        "id": "Q5341295",
        "label": "educational organization"
      },
      {
        "id": "Q35798",
        "label": "executive branch"
      },
      {
        "id": "Q17362920",
        "label": "Wikimedia duplicated page"
      },
      {
        "id": "Q11024",
        "label": "communication"
      },
      {
        "id": "Q921513",
        "label": "social organism behavior"
      },
      {
        "id": "Q23005223",
        "label": "division of an educational institution"
      },
      {
        "id": "Q2204117",
        "label": "symmetric tensor"
      },
      {
        "id": "Q188524",
        "label": "tensor"
      },
      {
        "id": "Q865811",
        "label": "distribution"
      },
      {
        "id": "Q170084",
        "label": "generalization"
      },
      {
        "id": "Q670",
        "label": "silicon"
      },
      {
        "id": "Q19596",
        "label": "metalloid"
      },
      {
        "id": "Q15708736",
        "label": "public authority"
      },
      {
        "id": "Q15621286",
        "label": "intellectual work"
      },
      {
        "id": "Q830077",
        "label": "subject"
      },
      {
        "id": "Q123705",
        "label": "neighborhood"
      },
      {
        "id": "Q18587469",
        "label": "residential community"
      },
      {
        "id": "Q486902",
        "label": "mathematical model"
      },
      {
        "id": "Q2996394",
        "label": "biological process"
      },
      {
        "id": "Q838123",
        "label": "data redundancy"
      },
      {
        "id": "Q1325769",
        "label": "antisymmetric tensor"
      },
      {
        "id": "Q981351",
        "label": "symmetric function"
      },
      {
        "id": "Q106693",
        "label": "group 14"
      },
      {
        "id": "Q3258231",
        "label": "Poisson binomial distribution"
      },
      {
        "id": "Q755707",
        "label": "municipality of Norway"
      },
      {
        "id": "Q42848",
        "label": "data"
      },
      {
        "id": "Q281801",
        "label": "botanical name"
      },
      {
        "id": "Q23729754",
        "label": "scientific name, published under a Code of nomenclature"
      },
      {
        "id": "Q1260632",
        "label": "content"
      },
      {
        "id": "Q7631075",
        "label": "administrative territorial entity of Switzerland"
      },
      {
        "id": "Q483247",
        "label": "phenomenon"
      },
      {
        "id": "Q15138389",
        "label": "Wikimedia article page"
      },
      {
        "id": "Q17379835",
        "label": "Wikimedia page outside the main knowledge tree"
      },
      {
        "id": "Q631147",
        "label": "infraspecific name"
      },
      {
        "id": "Q12562330",
        "label": "asymmetry property"
      },
      {
        "id": "Q2091629",
        "label": "magnitude"
      },
      {
        "id": "Q6545185",
        "label": "unique identifier"
      },
      {
        "id": "Q183046",
        "label": "meaning"
      },
      {
        "id": "Q239825",
        "label": "period 4"
      },
      {
        "id": "Q7590",
        "label": "transport"
      },
      {
        "id": "Q9332",
        "label": "behavior"
      },
      {
        "id": "Q15416",
        "label": "television program"
      },
      {
        "id": "Q21281405",
        "label": "Wikidata internal entity"
      },
      {
        "id": "Q17442446",
        "label": "Wikimedia internal item"
      },
      {
        "id": "Q192611",
        "label": "constituency"
      },
      {
        "id": "Q2324993",
        "label": "state power"
      },
      {
        "id": "Q2101636",
        "label": "political power"
      },
      {
        "id": "Q1318295",
        "label": "narrative"
      },
      {
        "id": "Q1200750",
        "label": "description"
      },
      {
        "id": "Q728646",
        "label": "partnership"
      },
      {
        "id": "Q321839",
        "label": "accord"
      },
      {
        "id": "Q21522864",
        "label": "class or metaclass of Wikidata ontology"
      },
      {
        "id": "Q1151067",
        "label": "rule"
      },
      {
        "id": "Q774228",
        "label": "requirement"
      },
      {
        "id": "Q6498784",
        "label": "mathematical expression"
      },
      {
        "id": "Q478798",
        "label": "image"
      },
      {
        "id": "Q1166770"
      },
      {
        "id": "Q46737",
        "label": "asset"
      },
      {
        "id": "Q1725664",
        "label": "terminology"
      },
      {
        "id": "Q28980086",
        "label": "RTC film classification category"
      },
      {
        "id": "Q23649976",
        "label": "content rating category"
      },
      {
        "id": "Q211331",
        "label": "period 3"
      },
      {
        "id": "Q16686022",
        "label": "natural physical object"
      },
      {
        "id": "Q163359",
        "label": "local administrative unit in the NUTS system"
      },
      {
        "id": "Q42032",
        "label": "country code top-level domain"
      },
      {
        "id": "Q190429",
        "label": "depression"
      },
      {
        "id": "Q349047"
      },
      {
        "id": "Q55659167",
        "label": "natural watercourse"
      },
      {
        "id": "Q355304",
        "label": "watercourse"
      },
      {
        "id": "Q16334295",
        "label": "group of humans"
      },
      {
        "id": "Q4330518",
        "label": "research object"
      },
      {
        "id": "Q8162",
        "label": "linguistics"
      },
      {
        "id": "Q147276",
        "label": "proper noun"
      },
      {
        "id": "Q28129886",
        "label": "proper name"
      },
      {
        "id": "Q82799",
        "label": "name"
      },
      {
        "id": "Q11033",
        "label": "mass media"
      },
      {
        "id": "Q79782",
        "label": "motion"
      },
      {
        "id": "Q17329259",
        "label": "encyclopedic article"
      },
      {
        "id": "Q10389811",
        "label": "entry"
      },
      {
        "id": "Q941",
        "label": "yttrium"
      },
      {
        "id": "Q108307",
        "label": "group 3"
      },
      {
        "id": "Q1184840",
        "label": "military vehicle"
      },
      {
        "id": "Q19829914",
        "label": "Wikidata property for places"
      },
      {
        "id": "Q52511956",
        "label": "Wikidata property related to geography"
      },
      {
        "id": "Q24229398",
        "label": "agent"
      },
      {
        "id": "Q2944660",
        "label": "lexical item"
      },
      {
        "id": "Q23683472",
        "label": "CERO rating category"
      },
      {
        "id": "Q11081619",
        "label": "land"
      },
      {
        "id": "Q1453431",
        "label": "defensive weapon"
      },
      {
        "id": "Q728",
        "label": "weapon"
      },
      {
        "id": "Q30892871",
        "label": "inhabited area"
      },
      {
        "id": "Q131222",
        "label": "information theory"
      },
      {
        "id": "Q18340964",
        "label": "power"
      },
      {
        "id": "Q19902884",
        "label": "Wikidata property definition"
      },
      {
        "id": "Q4167410",
        "label": "Wikimedia disambiguation page"
      },
      {
        "id": "Q1125239",
        "label": "public body"
      },
      {
        "id": "Q1937453",
        "label": "vehicle armor"
      },
      {
        "id": "Q627436",
        "label": "field of work"
      },
      {
        "id": "Q309314",
        "label": "quantity"
      },
      {
        "id": "Q33005760",
        "label": "narration"
      },
      {
        "id": "Q4189293",
        "label": "title"
      },
      {
        "id": "Q23960977",
        "label": "(meta)class"
      },
      {
        "id": "Q8148",
        "label": "industry"
      },
      {
        "id": "Q47657",
        "label": "blood type"
      },
      {
        "id": "Q13582682",
        "label": "classification"
      },
      {
        "id": "Q23959932",
        "label": "fixed-order metaclass"
      },
      {
        "id": "Q3505845",
        "label": "state"
      },
      {
        "id": "Q16512470",
        "label": "rule"
      },
      {
        "id": "Q4184950",
        "label": "regularity"
      },
      {
        "id": "Q863944",
        "label": "land waters"
      },
      {
        "id": "Q1789452",
        "label": "criterion"
      },
      {
        "id": "Q8171",
        "label": "word"
      },
      {
        "id": "Q43749575",
        "label": "veřejná obchodní společnost"
      },
      {
        "id": "Q646164",
        "label": "general partnership"
      },
      {
        "id": "Q3409032",
        "label": "unisex given name"
      },
      {
        "id": "Q28555911",
        "label": "ordinary matter"
      },
      {
        "id": "Q20026918",
        "label": "mathematical theory"
      },
      {
        "id": "Q4022",
        "label": "river"
      },
      {
        "id": "Q22294683",
        "label": "intraspecies interaction between organisms"
      },
      {
        "id": "Q30060700",
        "label": "object of science"
      },
      {
        "id": "Q20793164",
        "label": "armor"
      },
      {
        "id": "Q23009538",
        "label": "addition"
      },
      {
        "id": "Q3769299",
        "label": "human behaviour"
      },
      {
        "id": "Q629",
        "label": "oxygen"
      },
      {
        "id": "Q6005984",
        "label": "baryonic matter"
      },
      {
        "id": "Q28921572",
        "label": "common matter"
      },
      {
        "id": "Q22269697",
        "label": "multi-organism process"
      },
      {
        "id": "Q503992",
        "label": "name"
      },
      {
        "id": "Q12766313",
        "label": "geomorphological unit"
      },
      {
        "id": "Q19831450",
        "label": "human blood type"
      },
      {
        "id": "Q1921834",
        "label": "feature"
      },
      {
        "id": "Q4254715",
        "label": "Gourdou-Leseurre Type A"
      },
      {
        "id": "Q223662",
        "label": "SI base unit"
      },
      {
        "id": "Q3257686",
        "label": "locality"
      },
      {
        "id": "Q15324",
        "label": "body of water"
      },
      {
        "id": "Q15640612",
        "label": "fifth-level administrative country subdivision"
      },
      {
        "id": "Q48204",
        "label": "association"
      },
      {
        "id": "Q175185",
        "label": "rural area"
      },
      {
        "id": "Q21143058",
        "label": "agreement"
      },
      {
        "id": "Q930933",
        "label": "relation"
      },
      {
        "id": "Q218005",
        "label": "sum"
      },
      {
        "id": "Q813912",
        "label": "condition"
      },
      {
        "id": "Q533309",
        "label": "administrative territorial entity of Norway"
      },
      {
        "id": "Q11879590",
        "label": "female given name"
      },
      {
        "id": "Q19600",
        "label": "nonmetal"
      },
      {
        "id": "Q616622",
        "label": "first-person narrative"
      },
      {
        "id": "Q207712",
        "label": "period 2"
      },
      {
        "id": "Q188507",
        "label": "apartment"
      },
      {
        "id": "Q271669",
        "label": "landform"
      },
      {
        "id": "Q11618417",
        "label": "LAU 2"
      },
      {
        "id": "Q2145290",
        "label": "mental representation"
      },
      {
        "id": "Q1554231",
        "label": "resource"
      },
      {
        "id": "Q18336849",
        "label": "item with given name property"
      },
      {
        "id": "Q36774",
        "label": "web page"
      },
      {
        "id": "Q618779",
        "label": "award"
      },
      {
        "id": "Q81163",
        "label": "polymer"
      },
      {
        "id": "Q9420",
        "label": "thought"
      },
      {
        "id": "Q1047113",
        "label": "specialty"
      },
      {
        "id": "Q3711325",
        "label": "speed"
      },
      {
        "id": "Q3062125",
        "label": "farming business"
      },
      {
        "id": "Q146439",
        "label": "silicone"
      },
      {
        "id": "Q3387041",
        "label": "intensive quantity"
      },
      {
        "id": "Q2916486",
        "label": "administrative territorial entity of Turkey"
      },
      {
        "id": "Q1529096",
        "label": "köy"
      },
      {
        "id": "Q35825432",
        "label": "converter"
      },
      {
        "id": "Q35145263",
        "label": "natural geographic object"
      },
      {
        "id": "Q12139612",
        "label": "list"
      },
      {
        "id": "Q203872",
        "label": "being"
      },
      {
        "id": "Q3302947",
        "label": "audio recording"
      },
      {
        "id": "Q859031",
        "label": "stimulus"
      },
      {
        "id": "Q2006324"
      },
      {
        "id": "Q19776628",
        "label": "Latin-script letter"
      },
      {
        "id": "Q21162272"
      },
      {
        "id": "Q17164790",
        "label": "sign"
      },
      {
        "id": "Q7893853",
        "label": "univariate distribution"
      },
      {
        "id": "Q17737",
        "label": "theory"
      },
      {
        "id": "Q208218",
        "label": "patch"
      },
      {
        "id": "Q1381898",
        "label": "Marlon Pérez Arango"
      },
      {
        "id": "Q28829877",
        "label": "sports terminology"
      },
      {
        "id": "Q15229207",
        "label": "sports award"
      }
    ]
  }
}